gen/__init__.py
gen/cli.py
gen/config.py
gen/commands/__init__.py
gen/commands/helper.py
gen/commands/list_.py
gen/commands/template.py
gen/templates/__init__.py
gen/templates/__pycache__/__init__.cpython-313.pyc
gen/templates/c/main.c
gen/templates/cp/cp/README.md
gen/templates/cp/cp/in.txt
gen/templates/cp/cp/main.c
gen/templates/cp/cp/main.cpp
gen/templates/cp/cp/main.py
gen/templates/cp/cp/out.txt
gen/templates/cpp/main.cpp
gen/templates/go/main.go
gen/templates/html/main.html
gen/templates/java/main.java
gen/templates/javascript/main.js
gen/templates/python/main.py
gen/templates/python/flask/app.py
gen/templates/python/flask/static/style.css
gen/templates/python/flask/templates/index.html
gen/templates/rust/main.rs
gen_cli-0.1.2.dist-info/licenses/LICENSE
gen_cli-0.1.2.dist-info/METADATA
gen_cli-0.1.2.dist-info/WHEEL
gen_cli-0.1.2.dist-info/entry_points.txt
gen_cli-0.1.2.dist-info/top_level.txt
gen_cli-0.1.2.dist-info/RECORD
