Metadata-Version: 2.4
Name: gen-cli
Version: 0.1.2
Summary: Gen-CLI is a Python-based tool to generate boilerplate code and framework templates for multiple programming languages.
Author: Prasad Raju G
License: MIT License
Requires-Python: >=3.13
License-File: LICENSE
Dynamic: license-file
